{
	"ulid": "01DM3RA5ETFK428GBKV68WVVCK",
	"minTime": 1567761731164,
	"maxTime": 1567771200000,
	"stats": {
		"numSamples": 1274610,
		"numSeries": 5399,
		"numChunks": 8875
	},
	"compaction": {
		"level": 2,
		"sources": [
			"01DM38CQ12E2ZJ4EVKP930Q9DF",
			"01DM3BGNAXBSNCZMDZFP6PH99R"
		],
		"parents": [
			{
				"ulid": "01DM38CQ12E2ZJ4EVKP930Q9DF",
				"minTime": 1567761731164,
				"maxTime": 1567764000000
			},
			{
				"ulid": "01DM3BGNAXBSNCZMDZFP6PH99R",
				"minTime": 1567764000000,
				"maxTime": 1567771200000
			}
		]
	},
	"version": 1
}